MANIFEST.in
NEWS.txt
README.rst
setup.py
src/git_sweep.egg-info/PKG-INFO
src/git_sweep.egg-info/SOURCES.txt
src/git_sweep.egg-info/dependency_links.txt
src/git_sweep.egg-info/entry_points.txt
src/git_sweep.egg-info/not-zip-safe
src/git_sweep.egg-info/requires.txt
src/git_sweep.egg-info/top_level.txt
src/gitsweep/__init__.py
src/gitsweep/base.py
src/gitsweep/cli.py
src/gitsweep/deleter.py
src/gitsweep/entrypoints.py
src/gitsweep/inspector.py
src/gitsweep/scripts/__init__.py
src/gitsweep/scripts/test.py
src/gitsweep/tests/__init__.py
src/gitsweep/tests/test_cli.py
src/gitsweep/tests/test_deleter.py
src/gitsweep/tests/test_inspector.py
src/gitsweep/tests/testcases.py