Metadata-Version: 1.0
Name: git-sweep
Version: 0.1.1
Summary: Clean up branches from your Git remotes
Home-page: http://arc90.com
Author: Arc90, Inc.
Author-email: UNKNOWN
License: MIT
Keywords: git maintenance branches
Platform: UNKNOWN
Classifier: Development Status :: 4 - Beta
Classifier: Environment :: Console
Classifier: License :: OSI Approved :: MIT License
Classifier: Intended Audience :: Developers
Classifier: Natural Language :: English
Classifier: Operating System :: POSIX
Classifier: Programming Language :: Python :: 2.6
Classifier: Programming Language :: Python :: 2.7
Classifier: Topic :: Software Development :: Quality Assurance
Classifier: Topic :: Software Development :: Version Control
Classifier: Topic :: Text Processing
